eigendata/__init__.py
eigendata/_version.py
eigendata/labextension/package.json
eigendata/labextension/schemas/@molinsp/eigendata/package.json.orig
eigendata/labextension/schemas/@molinsp/eigendata/settings.json
eigendata/labextension/schemas/@molinsp/eigendata/usertransformations.json
eigendata/labextension/static/060b2710bdbbe3dfe48b58d59bd5f1fb.svg
eigendata/labextension/static/106.0513c923761221bb2ca5.js
eigendata/labextension/static/122.28f040b4a5ff3e27b74b.js
eigendata/labextension/static/197.52af4b4f3f39ba24e0cc.js
eigendata/labextension/static/197.52af4b4f3f39ba24e0cc.js.LICENSE.txt
eigendata/labextension/static/251.2b4fa6e7467345f3c433.js
eigendata/labextension/static/251.2b4fa6e7467345f3c433.js.LICENSE.txt
eigendata/labextension/static/288.7b101919d2e73e109ba8.js
eigendata/labextension/static/331.a55dc63629cecfe14fe1.js
eigendata/labextension/static/4692b9ec53fd5972caa2f2372ae20d16.ttf
eigendata/labextension/static/494.733424aa48c1872cbe09.js
eigendata/labextension/static/494.733424aa48c1872cbe09.js.LICENSE.txt
eigendata/labextension/static/495.9f11e93a83aac5f9fd95.js
eigendata/labextension/static/521.67dad3defa785dc49a6c.js
eigendata/labextension/static/534.a39b42fe83dda71cced0.js
eigendata/labextension/static/5be1347c682810f199c7f486f40c5974.eot
eigendata/labextension/static/635.4ab8e07cf173f36ee86c.js
eigendata/labextension/static/700.2d5f8ccb0a1df6716e1a.js
eigendata/labextension/static/791.6af1faf4138922e8df02.js
eigendata/labextension/static/791.6af1faf4138922e8df02.js.LICENSE.txt
eigendata/labextension/static/817.ddcc806278faf8ef57e2.js
eigendata/labextension/static/82b1212e45a2bc35dd731913b27ad813.woff
eigendata/labextension/static/864.0fe28255c00460ea050f.js
eigendata/labextension/static/864.0fe28255c00460ea050f.js.LICENSE.txt
eigendata/labextension/static/889.7451506fb61a7111e827.js
eigendata/labextension/static/889.7451506fb61a7111e827.js.LICENSE.txt
eigendata/labextension/static/954.0e14a9eea810955ae89e.js
eigendata-0.3.9.dist-info/LICENSE
eigendata-0.3.9.dist-info/METADATA
eigendata-0.3.9.dist-info/WHEEL
eigendata-0.3.9.dist-info/top_level.txt
eigendata-0.3.9.dist-info/RECORD
