Metadata-Version: 2.1
Name: eigendata
Version: 0.3.9
Summary: Eigendata is a low-code tool for data analysis designed for people that want to get things done.
Home-page: https://molinsp.github.io/eigendata-doc/
Author: Pere Molins
Author-email: pere@eigendata.co
License: BSD-3-Clause
Keywords: Jupyter,JupyterLab,JupyterLab3
Platform: Linux
Platform: Mac OS X
Platform: Windows
Classifier: License :: OSI Approved :: BSD License
Classifier: Programming Language :: Python
Classifier: Programming Language :: Python :: 3
Classifier: Programming Language :: Python :: 3.6
Classifier: Programming Language :: Python :: 3.7
Classifier: Programming Language :: Python :: 3.8
Classifier: Programming Language :: Python :: 3.9
Classifier: Framework :: Jupyter
Requires-Python: >=3.6
License-File: LICENSE
Requires-Dist: jupyter-server (<2,>=1.6)
Requires-Dist: numpy (>=1.0.0)
Requires-Dist: pandas (>=1.0.0)
Requires-Dist: fastdata (>=0.0.20)
